Metadata-Version: 1.0
Name: srg-distributions
Version: 0.1
Summary: Gaussian distributions
Home-page: UNKNOWN
Author: sergethiPytest
Author-email: nsergearistide@gmail.com
License: UNKNOWN
Platform: UNKNOWN
